ph5lt/__init__.py
ph5lt/__main__.py
ph5lt/allowlists.py
ph5lt/app.py
ph5lt/banner.py
ph5lt/blocklists.py
ph5lt/constants.py
ph5lt/prompts.py
ph5lt/stats.py
ph5lt/utils.py
pihole5_list_tool-0.6.2.dist-info/LICENSE
pihole5_list_tool-0.6.2.dist-info/METADATA
pihole5_list_tool-0.6.2.dist-info/WHEEL
pihole5_list_tool-0.6.2.dist-info/entry_points.txt
pihole5_list_tool-0.6.2.dist-info/top_level.txt
pihole5_list_tool-0.6.2.dist-info/RECORD
