Metadata-Version: 2.1
Name: pihole5-list-tool
Version: 0.6.2
Summary: A tool for quickly and easily bulk adding allowlists and ad/blocklists to a Pi-hole 5 installation
Home-page: https://github.com/jessedp/pihole5-list-tool
Author: jessedp
Author-email: jessedp@gmail.com
License: UNKNOWN
Project-URL: Bug Tracker, https://github.com/jessedp/pihole5-list-tool/issues
Project-URL: Source Code, https://github.com/jessedp/pihole5-list-tool
Keywords: pihole,pi-hole,blacklist,blocklist,whitelist,allowlist,adlist
Platform: UNKNOWN
Classifier: Programming Language :: Python :: 3
Classifier: License :: OSI Approved :: MIT License
Classifier: Operating System :: OS Independent
Classifier: Topic :: Utilities
Classifier: Topic :: Internet :: Name Service (DNS)
Requires-Python: >=3.7
License-File: LICENSE
Requires-Dist: InquirerPy
Requires-Dist: ansicolors
Requires-Dist: requests
Requires-Dist: terminaltables
